crypt_dozer/__init__.py
crypt_dozer/main.py
crypt_dozer-1.0.0.dist-info/LICENSE
crypt_dozer-1.0.0.dist-info/METADATA
crypt_dozer-1.0.0.dist-info/WHEEL
crypt_dozer-1.0.0.dist-info/top_level.txt
crypt_dozer-1.0.0.dist-info/RECORD
