Metadata-Version: 2.1
Name: crypt_dozer
Version: 1.0.0
Summary: A simple package for encrypting and decrypting data using the cryptography library
Home-page: https://github.com/sathvik/crypt_dozer
Author: Sathvik
Author-email: sathvik@dview.io
License: MIT
Classifier: Programming Language :: Python :: 3
Classifier: License :: OSI Approved :: MIT License
Classifier: Operating System :: OS Independent
Requires-Python: >=3.6
License-File: LICENSE
Provides-Extra: dev
Requires-Dist: pytest; extra == "dev"
